{
	"id": "ukg-bill-api-environment",
	"name": "UKG & BILL.com API Environment",
	"values": [
		{
			"key": "UKG_BASE_URL",
			"value": "https://service4.ultipro.com",
			"type": "default",
			"enabled": true,
			"description": "UKG Pro API base URL"
		},
		{
			"key": "UKG_USERNAME",
			"value": "",
			"type": "secret",
			"enabled": true,
			"description": "UKG Pro API username"
		},
		{
			"key": "UKG_PASSWORD",
			"value": "",
			"type": "secret",
			"enabled": true,
			"description": "UKG Pro API password"
		},
		{
			"key": "UKG_BASIC_AUTH",
			"value": "",
			"type": "secret",
			"enabled": true,
			"description": "Base64 encoded username:password for Basic Auth. Generate using: echo -n 'username:password' | base64"
		},
		{
			"key": "UKG_CUSTOMER_API_KEY",
			"value": "",
			"type": "secret",
			"enabled": true,
			"description": "UKG Customer API Key (US-Customer-Api-Key header)"
		},
		{
			"key": "BILL_BASE_URL",
			"value": "https://gateway.stage.bill.com/connect/v3",
			"type": "default",
			"enabled": true,
			"description": "BILL.com API base URL. Use 'gateway.stage.bill.com' for staging, 'gateway.bill.com' for production"
		},
		{
			"key": "BILL_API_TOKEN",
			"value": "",
			"type": "secret",
			"enabled": true,
			"description": "BILL.com API Token (apiToken header)"
		},
		{
			"key": "company_id",
			"value": "COMP1",
			"type": "default",
			"enabled": true,
			"description": "Company ID for UKG API calls"
		},
		{
			"key": "employee_id",
			"value": "",
			"type": "default",
			"enabled": true,
			"description": "Employee UUID for UKG person-details API"
		},
		{
			"key": "employee_number",
			"value": "",
			"type": "default",
			"enabled": true,
			"description": "Employee number for UKG employment-details API"
		},
		{
			"key": "user_id",
			"value": "",
			"type": "default",
			"enabled": true,
			"description": "BILL.com user UUID for S&E API"
		},
		{
			"key": "vendor_id",
			"value": "",
			"type": "default",
			"enabled": true,
			"description": "BILL.com vendor ID for AP API"
		},
		{
			"key": "bill_id",
			"value": "",
			"type": "default",
			"enabled": true,
			"description": "BILL.com bill/invoice ID for AP API"
		},
		{
			"key": "payment_id",
			"value": "",
			"type": "default",
			"enabled": true,
			"description": "BILL.com payment ID for AP API"
		}
	],
	"_postman_variable_scope": "environment",
	"_postman_exported_at": "2024-02-01T00:00:00.000Z",
	"_postman_exported_using": "Manual Export"
}
